moisten/__init__.py
moisten/calc/__init__.py
moisten/calc/_calc.py
moisten/calc/_xr.py
moisten/calc/constant.py
moisten/utils/logger.py
moisten/utils/timer.py
moisten/utils/viewer.py
moisten-2.0.1.dist-info/licenses/LICENSE
moisten-2.0.1.dist-info/METADATA
moisten-2.0.1.dist-info/WHEEL
moisten-2.0.1.dist-info/top_level.txt
moisten-2.0.1.dist-info/RECORD
