Metadata-Version: 2.4
Name: moisten
Version: 2.0.1
Summary: A toolbox for atmospheric scientists, including data processing and plotting functions.
Project-URL: Repository, https://gitee.com/lilidream/moisten
Requires-Python: >=3.12
License-File: LICENSE
Requires-Dist: xarray>=2024.03.0
Requires-Dist: numpy>=2.1.0
Requires-Dist: rich>=13.8.0
Requires-Dist: matplotlib>=3.10.0
Requires-Dist: moisten-plot>=0.1.3
Requires-Dist: moisten-ew>=0.1.3
Dynamic: license-file
